cloudevents/__init__.py
cloudevents/http/__init__.py
cloudevents/http/event.py
cloudevents/http/http_methods.py
cloudevents/http/json_methods.py
cloudevents/http/mappings.py
cloudevents/http/util.py
cloudevents/sdk/__init__.py
cloudevents/sdk/exceptions.py
cloudevents/sdk/marshaller.py
cloudevents/sdk/types.py
cloudevents/sdk/converters/__init__.py
cloudevents/sdk/converters/base.py
cloudevents/sdk/converters/binary.py
cloudevents/sdk/converters/structured.py
cloudevents/sdk/event/__init__.py
cloudevents/sdk/event/base.py
cloudevents/sdk/event/opt.py
cloudevents/sdk/event/v03.py
cloudevents/sdk/event/v1.py
curtiscloudevents-1.0.11.dist-info/LICENSE
curtiscloudevents-1.0.11.dist-info/METADATA
curtiscloudevents-1.0.11.dist-info/WHEEL
curtiscloudevents-1.0.11.dist-info/top_level.txt
curtiscloudevents-1.0.11.dist-info/RECORD
